[{"축제명":"홍성남당항새조개축제","지역":"충청남도","장소":"남당항 일원","축제내용":"새조개까기체험, 관광객 노래자랑, 새조개 시식회 등","홈피주소":"","위도":"36.53503195","경도":"126.467178"},{"축제명":"제24회 보령머드축제","지역":"충청남도","장소":"충청남도 보령시 대천해수욕장 일원","축제내용":"머드체험시설 및 갯벌체험 등","홈피주소":"http://www.mudfestival.or.kr","위도":"36.304497","경도":"126.517028"},{"축제명":"금산인삼축제","지역":"충청남도","장소":"금산인삼관 광장 및 인삼약초시장 일원","축제내용":"ㅇ인삼캐기체험, 건강체험관, 어린이힐링놀이터,인삼아트거리 등 체험ㅇ건강댄스경연,힐링콘서트, 전국창작동요경연대회 등 경연,공연ㅇ국제인삼교역전, 인삼왕수상작 전시 등 전시교역","홈피주소":"http://www.insamfestival.co.kr/","위도":"36.1000256","경도":"127.5007304"},{"축제명":"비단고을산꽃축제","지역":"충청남도","장소":"군북면 산꽃벚꽃마을 오토캠핑장","축제내용":"ㅇ산꽃 개화 상황 온라인 방송, 산꽃테마길 스탬프 투어, 나만의 반려식물 가꾸기, 숲 속 작은 음악회, 산꽃술개길 건강걷기대회 등","홈피주소":"http://www.insamfestival.co.kr/","위도":"36.19093401","경도":"127.5710874"},{"축제명":"금산천봄꽃축제","지역":"충청남도","장소":"금산읍 금산천 일원","축제내용":"ㅇ봄꽃노래자랑, 소원꽃잎적기, 주민자치센터공연, 봄꽃카페 등","홈피주소":"","위도":"36.1020211","경도":"127.4843123"},{"축제명":"남일면홍도화축제","지역":"충청남도","장소":"남일면 홍도마을 일원","축제내용":"ㅇ홍도화가요제, 홍도화 길 꽃마차, 송어잡기체험, 나무곤충만들기 등","홈피주소":"","위도":"36.0171101","경도":"127.5180376"},{"축제명":"연산백중놀이","지역":"충청남도","장소":"연산전통시장","축제내용":"연산백중놀이 정기공연","홈피주소":"","위도":"36.2162708","경도":"127.216078"},{"축제명":"강경젓갈축제","지역":"충청남도","장소":"강경읍일원","축제내용":"강경젓갈 우수성 홍보","홈피주소":"https://www.nonsan.go.kr/eggfestival/","위도":"36.15755625","경도":"127.0098063"},{"축제명":"춘장대해수욕장 여름문화예술축제","지역":"충청남도","장소":"춘장대해수욕장 중앙광장","축제내용":"한여름밤의 트롯이야기, 춘장대 시네마, 춘장대 푸파 페스티벌 등","홈피주소":"http://tour.seocheon.go.kr","위도":"36.16334922","경도":"126.5243355"},{"축제명":"자연산 광어.도미 축제","지역":"충청남도","장소":"서면 마량포구 일원","축제내용":"맨손으로 광어잡기 체험, 기념공원에서 보물찾기","홈피주소":"http://tour.seocheon.go.kr","위도":"36.1293642","경도":"126.5036472"},{"축제명":"마량포 해넘이.해돋이 축제","지역":"충청남도","장소":"서면 마량포구 일원","축제내용":"새해 떡국나눔행사, 불꽃놀이, 버스킹 공연, 소원등 달기","홈피주소":"http://tour.seocheon.go.kr","위도":"36.1293642","경도":"126.5036472"},{"축제명":"홍원항 자연산 전어.꽃게 축제","지역":"충청남도","장소":"서면 홍원항 일원","축제내용":"맨손으로 전어 잡기 체험, 추억의 놀이 체험, 숨겨진 보물을 찾아라, 비눗방울 놀이 등","홈피주소":"http://tour.seocheon.go.kr","위도":"36.1588617963","경도":"126.4992204"},{"축제명":"한산모시문화제","지역":"충청남도","장소":"한산모시관 일원","축제내용":"한산모시를 주제로 하는 다양한 프로그램 운영","홈피주소":"www.hansanmosi.kr/","위도":"36.0799445","경도":"126.7987047"},{"축제명":"서천철새여행","지역":"충청남도","장소":"조류생태전시관 일원","축제내용":"철새 탐조 및 철새 관련 문화행사","홈피주소":"http://tour.seocheon.go.kr","위도":"36.02280046","경도":"126.7426918"},{"축제명":"서산해미읍성축제","지역":"충청남도","장소":"서산시 해미면 남문2로 143(해미읍성)","축제내용":"주제체험, 기획프로그램, 전통문화공연 등","홈피주소":"http://www.haemifest.com/","위도":"36.71355717","경도":"126.5503842"},{"축제명":"서산국화축제","지역":"충청남도","장소":"서산시 고북면 가구리 52(한농원)","축제내용":"과수원을 배경으로 실내·외 국화전시, 체험프로그램 및 문화·예술 공연 등","홈피주소":"http://gukhwaou.blog.me/","위도":"36.66936247","경도":"126.536256"},{"축제명":"부여서동연꽃축제","지역":"충청남도","장소":"서동공원","축제내용":"연꽃과 서동선화의 사랑이야기를 담은 각종 전시, 공연, 체험 등","홈피주소":"www.부여서동연꽃축제.kr","위도":"36.27145891","경도":"126.9136908"},{"축제명":"백제문화제","지역":"충청남도","장소":"정림사지 박물관 일원","축제내용":"사비 백제 역사를 담은 문화제","홈피주소":"http://www.baekje.org/html/kr/","위도":"36.27902473","경도":"126.9128811"},{"축제명":"태안 세계툴립축제","지역":"충청남도","장소":"꽃지해수욕장 해안공원","축제내용":"태안 화훼(튤립) 전시·체험 행사 등","홈피주소":"없음","위도":"36.50112252","경도":"126.3367861"},{"축제명":"홍성남당항새조개축제","지역":"충청남도","장소":"남당항 일원","축제내용":"새조개 까기 체험 및 다양한 체험·공연 진행(갯벌체험, 새조개껍질리폼체험 등)","홈피주소":"없음","위도":"36.53503195","경도":"126.467178"},{"축제명":"예산 장터삼국축제","지역":"충청남도","장소":"예산전통시장 내","축제내용":"예산장터 국밥, 예산 국수, 예산 국화의 3가지 국을 테마로 한 예산 장터 축제","홈피주소":"없음","위도":"36.67611933","경도":"126.8479256"},{"축제명":"아산성웅이순신축제","지역":"충청남도","장소":"온양온천역 광장 및 시내일원","축제내용":"승전행렬 퍼레이드, 개폐막공연, 전시체험 및 기타부대행사","홈피주소":"http://culture.asan.go.kr/_esunshin/2017/index.asp","위도":"36.7804682813","경도":"127.0034511105"},{"축제명":"신정호 별빛축제","지역":"충청남도","장소":"아산시 신정호 야외음악당 및 잔디 일원","축제내용":"영화상영, 시네마토크, 지역예술단체공연","홈피주소":"http://culture.asan.go.kr/_sinjungho/","위도":"36.7715214106","경도":"126.9839151707"},{"축제명":"설화예술제","지역":"충청남도","장소":"신정호 야외음악당 및 이순신체육관","축제내용":"개폐막식, 지역예술인창작발표 공연 및 전시","홈피주소":"","위도":"36.7715214106","경도":"126.9839151707"},{"축제명":"도고 코미디 핫 페스트 IN 아산","지역":"충청남도","장소":"파라다이스도고 잔디광장","축제내용":"개폐막식, 코미디공연, 거리공연 및 부대행사","홈피주소":"http://showtimehall.co.kr/dcf/","위도":"36.76551565","경도":"126.8880000938"},{"축제명":"짚풀문화제","지역":"충청남도","장소":"아산 외암민속마을","축제내용":"전통혼례재연·떡메치기 등 33여개 전통체험운영, 짚풀공예품 등 각종 전시, 국악공연·마물놀이 등 공연","홈피주소":"http://oeam.co.kr/oeam/skin1/sub_page.php?page_idx=267","위도":"36.73099329","경도":"127.014409"},{"축제명":"백제문화제(공주)","지역":"충청남도","장소":"금강신관공원 및 공산성 일원","축제내용":"제례불전, 비대면 온라인 프로그램(웅진판타지아, 집콕라이브 골든벨) 등","홈피주소":"http://www.baekje.org","위도":"36.47021463","경도":"127.1274371"},{"축제명":"보령머드축제","지역":"충청남도","장소":"대천해수욕장 일원","축제내용":"코로나-19 대비 온라인 프로그램(유튜브채널 머드TV, 집콕머드체험,&공모전, 집콕머드라이브 등)","홈피주소":"www.mudfestival.or.kr","위도":"36.3155199","경도":"126.5108563"},{"축제명":"강경젓갈축제","지역":"충청남도","장소":"강경둔치 일원","축제내용":"집콕 강경젓갈김치 담그기 등 온택트 프로그램(유튜브채널 강경맛깔젓TV), 특가홍보판매전 등","홈피주소":"http://www.nonsan.go.kr/ggfestival/","위도":"36.15755616","경도":"127.0098062"},{"축제명":"백제문화제(보령)","지역":"충청남도","장소":"부여 구드래 일원","축제내용":"제례불전, 비대면 온라인 프로그램(태학박사 퀴즈, 랜선 문화나들이) 등","홈피주소":"http://www.baekje.org","위도":"36.28714312","경도":"126.9068121"},{"축제명":"왜목해돋이축제","지역":"충청남도","장소":"왜목마을 일대","축제내용":"소원지 태우기, 일출 감상, 떡국 나눔행사 등","홈피주소":"http://tour.dangjin.go.kr","위도":"37.0444338513","경도":"126.5261285051"},{"축제명":"기지시줄다리기 민속축제","지역":"충청남도","장소":"기지시줄다리기 박물관 일원","축제내용":"국수봉당제, 시장기원제, 그네뛰기 등 민속놀이, 스포츠 줄다리기, 줄고사, 줄나가기, 줄다리기 등","홈피주소":"http://www.gijisi.com","위도":"36.8961622787","경도":"126.694732"},{"축제명":"장고항 실치축제","지역":"충청남도","장소":"장고항 일대","축제내용":"맨손고기잡이, 수산물경매, 실치로 뱅어포 만들기, 사물놀이, 노래자랑 등","홈피주소":"http://tour.dangjin.go.kr","위도":"37.0288578290","경도":"126.5619917822"},{"축제명":"한진포구 바지락 갯벌체험축제","지역":"충청남도","장소":"한진포구 일대","축제내용":"바지락캐기, 바다낚시체험, 경품행사, 바지락요리시식회, 불꽃놀이","홈피주소":"http://tour.dangjin.go.kr","위도":"36.9703775430","경도":"126.7817211842"},{"축제명":"해나루 황토감자축제","지역":"충청남도","장소":"상록초등학교 일원","축제내용":"해나루 황토감자 캐기, 공연행사, 그림대회, 요리경연대회","홈피주소":"www.당진해나루황토감자축제.com","위도":"36.9585734449","경도":"126.7697651155"},{"축제명":"면천 진달래축제","지역":"충청남도","장소":"면천읍성 앞 광장 및 면천일원","축제내용":"진달래 사생대회 및 백일장, 진달래 어린이 장사 씨름대회, 진달래 청소년 가요제, 진달래 음식체험 등","홈피주소":"http://www.jindalae.co.kr","위도":"36.8176186464","경도":"126.666993"},{"축제명":"8.15. 프란치스코 데이","지역":"충청남도","장소":"솔뫼성지 일원","축제내용":"교황방문 영상시청, 체험담 나눔행사, 기념 음악회, 교황 방문기념 전시회 등","홈피주소":"http://www.solmoe.or.kr","위도":"36.8195680158","경도":"126.7865193238"},{"축제명":"심훈상록문화제","지역":"충청남도","장소":"당진시청 일원","축제내용":"심훈문학상 수상, 심훈상록수연극공연, 심훈청소년국악제 등","홈피주소":"http://www.djsangnok.org","위도":"36.889754","경도":"126.6459710322"},{"축제명":"삽교호조개구이 축제","지역":"충청남도","장소":"삽교호 관광지 일원","축제내용":"바지락옮기기, 망둥어 낚시, 방조제 걷기, 노래자랑 등","홈피주소":"http://tour.dangjin.go.kr","위도":"36.8906104460","경도":"126.8244108709"},{"축제명":"남이흥장군 문화제","지역":"충청남도","장소":"충장사 일원","축제내용":"조선무과체험, 전통무예재현, 태견, 씨름대회, 군악대 연주 등","홈피주소":"http://www.chungjanggong.or.kr","위도":"36.924978","경도":"126.529455"},{"축제명":"백제 어울마당","지역":"충청남도","장소":"공산성","축제내용":"백제기악 미마지탈극, 백제춤추기 체험 등","홈피주소":"","위도":"36.46521533","경도":"127.1236356"},{"축제명":"웅진성수문병 근무교대식","지역":"충청남도","장소":"공산성 금서루","축제내용":"수문병 근무교대식,백제왕.왕비복 체험,  옥사체험,    활쏘기 체험 등","홈피주소":"","위도":"36.46521533","경도":"127.1236802"},{"축제명":"공주 석장리 구석기축제","지역":"충청남도","장소":"석장리박물관","축제내용":"구석기문화 체험","홈피주소":"","위도":"36.44795221","경도":"127.1875895"},{"축제명":"계룡산산신제","지역":"충청남도","장소":"계룡면 양화리 신원사일원","축제내용":"유.불.무가식 산신제,점사체험, 기체험, 다양한 무대공연 등","홈피주소":"","위도":"36.333638","경도":"127.177107"},{"축제명":"마곡사 신록축제","지역":"충청남도","장소":"사곡면 운암리 마곡사일원","축제내용":"명상길 걷기,템플스테이, 전국 학생그림그리기 대회","홈피주소":"","위도":"36.55740589","경도":"127.011603"},{"축제명":"제63회 백제문화제","지역":"충청남도","장소":"금강신관공원","축제내용":"웅진성퍼레이드,체험마당, 무대공연,농특산품전시 및 판매","홈피주소":"","위도":"36.47021463","경도":"127.1274371"},{"축제명":"2017 겨울공주군밤축제","지역":"충청남도","장소":"금학생태공원","축제내용":"눈썰매장 및 겨울놀이시설 운영","홈피주소":"","위도":"36.43336915","경도":"127.124038"},{"축제명":"2018 백제어울마당","지역":"충청남도","장소":"송산리고분군(무령왕릉) 일원","축제내용":"미마지탈 만들고 써보기, 백제춤주기, 퓨전공연 등","홈피주소":"","위도":"36.46060505","경도":"127.1126907"},{"축제명":"2018 웅진성수문병 근무교대식","지역":"충청남도","장소":"공산성 금서루","축제내용":"수문병 근무교대식, 공산성 성벽극장 인형극, 관광객과 함께하는 어가행렬","홈피주소":"","위도":"36.46521533","경도":"127.1236802"},{"축제명":"2018 공주 석장리 세계구석기축제","지역":"충청남도","장소":"석장리박물관","축제내용":"네안데르탈인 특별전시전, 별빛토크쇼, 구석기문화 체험 등","홈피주소":"","위도":"36.44795221","경도":"127.1875895"},{"축제명":"2018 계룡산산신제","지역":"충청남도","장소":"계룡면 양화리 신원사일원","축제내용":"유.불.무가식 산신제,점사체험, 기체험, 다양한 무대공연 등","홈피주소":"","위도":"36.333638","경도":"127.177107"},{"축제명":"제15회 마곡사신록축제","지역":"충청남도","장소":"사곡면 운암리 마곡사일원","축제내용":"버스킹공연, 소나무심기, 야생화 전시, 농특산물 판매 등","홈피주소":"","위도":"36.55740589","경도":"127.011603"},{"축제명":"2018 계룡산벚꽃축제","지역":"충청남도","장소":"계룡산 동학사 일원","축제내용":"야간경관 설치, 계룡산벚꽃가요제, 분청사기 만들기, 먹거리 운영 등","홈피주소":"","위도":"36.36030634","경도":"127.2509274"},{"축제명":"2018 마곡사토요무대","지역":"충청남도","장소":"마곡사관광지 야외무대","축제내용":"버스킹공연, 프린지공연, 섹소폰 연주, 국악연주 등","홈피주소":"","위도":"36.55728753","경도":"127.0183843"},{"축제명":"제64회 백제문화제","지역":"충청남도","장소":"금강신관공원 및 공산성 일원","축제내용":"K-POP 한류페스티벌, 웅진성퍼레이드, 체험마당, 먹거리마당, 농특산물판매 등","홈피주소":"","위도":"36.47021463","경도":"127.1274371"},{"축제명":"2019겨울공주군밤축제","지역":"충청남도","장소":"고마아트센터","축제내용":"눈썰매장 및 겨울놀이시설 운영","홈피주소":"","위도":"36.43336915","경도":"127.124038"},{"축제명":"2019 백제어울마당","지역":"충청남도","장소":"송산리고분군(무령왕릉) 일원","축제내용":"미마지탈극, 무예극, 백제탈 체험 등","홈피주소":"","위도":"36.46060505","경도":"127.1126907"},{"축제명":"2019 웅진성수문병 근무교대식","지역":"충청남도","장소":"공산성 금서루","축제내용":"수문병 근무교대식, 체험프로그램 등","홈피주소":"","위도":"36.46521533","경도":"127.1236802"},{"축제명":"2019 공주 석장리 구석기축제","지역":"충청남도","장소":"석장리박물관","축제내용":"네안데르탈인 특별전시전, 별빛토크쇼, 구석기문화 체험 등","홈피주소":"","위도":"36.44795221","경도":"127.1875895"},{"축제명":"2019 계룡산산신제","지역":"충청남도","장소":"계룡면 양화리 신원사일원","축제내용":"유.불.무가식 산신제,점사체험, 다양한 무대공연 등","홈피주소":"","위도":"36.333638","경도":"127.177107"},{"축제명":"제16회 마곡사신록축제","지역":"충청남도","장소":"사곡면 운암리 마곡사일원","축제내용":"버스킹공연, 꽃화분, 야생화 전시, 보물찾기, 농특산물 판매 등","홈피주소":"","위도":"36.55740589","경도":"127.011603"},{"축제명":"2019 계룡산벚꽃축제","지역":"충청남도","장소":"계룡산 동학사 일원","축제내용":"야간경관 설치, 계룡산벚꽃가요제, 분청사기 만들기, 먹거리 운영 등","홈피주소":"","위도":"36.36030634","경도":"127.2509274"},{"축제명":"갑사황매화 축제","지역":"충청남도","장소":"갑사일원","축제내용":"문화공연, 체험, 갑사 과거사 사진전시회 등","홈피주소":"","위도":"36.36607692","경도":"127.1864443"},{"축제명":"공주항공축제","지역":"충청남도","장소":"공주경비행기장(정안천 일원)","축제내용":"경량항공기 활주로 주행체험, 포토존, 물로켓 만들기등","홈피주소":"","위도":"36.51052026","경도":"127.1258208"},{"축제명":"공주 금강여름축제","지역":"충청남도","장소":"고마아트센터","축제내용":"국악&재즈공연, 프린지공연, 밴드경연대회, 물놀이 체험및 전시, 먹거리 운영 등","홈피주소":"","위도":"36.55728753","경도":"127.0183843"},{"축제명":"제65회 백제문화제","지역":"충청남도","장소":"금강신관공원 및 공산성 일원","축제내용":"웅진파타지아, 웅진성퍼레이드, 체험마당, 먹거리마당, 농특산물판매 등","홈피주소":"","위도":"36.47021463","경도":"127.1274371"},{"축제명":"꽃지저녁노을축제","지역":"충청남도","장소":"꽃지해안공원","축제내용":"연날리기 및 떡국나누기","홈피주소":"","위도":"36.502448","경도":"126.335462"},{"축제명":"백화산 해맞이 행사","지역":"충청남도","장소":"백화산 정상","축제내용":"신년 해맞이 소원 풍선 날리기","홈피주소":"","위도":"36.7678646600","경도":"126.3017086527"},{"축제명":"연포 해맞이 행사","지역":"충청남도","장소":"연포해수욕장","축제내용":"신년 해맞이 소원 풍선 날리기","홈피주소":"","위도":"36.6943402716","경도":"126.2102393465"},{"축제명":"예산장터삼국축제","지역":"충청남도","장소":"예산전통시장","축제내용":"예산의 국화, 국밥, 국수의 맛과 멋을 찾아 예산장터로 떠나는 가을여행축제","홈피주소":"www.예산장터삼국축제.kr","위도":"36.67611933","경도":"126.8479256"},{"축제명":"의좋은형제축제","지역":"충청남도","장소":"의좋은 형제공원","축제내용":"예산의 실존인물인 이성만·이순형제와 함께 떠나는 가족여행","홈피주소":"","위도":"36.60651783","경도":"126.7872697"},{"축제명":"계룡군문화축제","지역":"충청남도","장소":"계룡대 비상활주로 일원","축제내용":"軍관련 공연, 전시, 체험행사 등","홈피주소":"http://www.m-festival.org/","위도":"36.274229","경도":"127.248827"}]